{
  "wallet_btc":"",
  "wallet_ltc":"",
  "wallet_bch":"",
  "wallet_zec":"",
  "wallet_doge":"",
  "reff_btc":"p3TgN",
  "reff_ltc":"UD1oQ",
  "reff_bch":"Oweq",
  "reff_doge":"DvTFj",
  "reff_zec":"ib6ft",
  "fitur":{
    "auto_reff":"on",
    "msg":"off",
    "join":"on",
    "visit":"off",
    "auto_wd":"off"
  },
  "jumlah":{
      "msg":"200",
      "join":"100",
      "visit":"200"
   },
  "cf-cookie":{
    "ua":"Mozilla/5.0 (Windows NT 10.0; Win64; x64; rv:88.0) Gecko/20100101 Firefox/88.0",
    "limit":"3",
    "delay":"60"
  }
}
